scope/__init__.py
scope/dir_size.py
scope/llm_utils.py
scope/main.py
scope/port_checker.py
scope/process_utils.py
scope_cli-0.2.3.dist-info/METADATA
scope_cli-0.2.3.dist-info/WHEEL
scope_cli-0.2.3.dist-info/entry_points.txt
scope_cli-0.2.3.dist-info/top_level.txt
scope_cli-0.2.3.dist-info/RECORD
