Metadata-Version: 2.1
Name: scope-cli
Version: 0.2.3
Summary: A CLI tool for visualizing directory sizes and checking port usage.
Home-page: https://github.com/deepampatel/scope-cli
Author: Deepam Patel
Author-email: deepam8155@gmail.com
Classifier: Programming Language :: Python :: 3
Classifier: License :: OSI Approved :: MIT License
Classifier: Operating System :: OS Independent
Requires-Python: >=3.6
Requires-Dist: click
Requires-Dist: psutil
Provides-Extra: llm
Requires-Dist: openai (>1.0.1) ; extra == 'llm'
Requires-Dist: colorama ; extra == 'llm'
